[{"place_id": 329300525, "licence": "Data \u00a9 OpenStreetMap contributors, ODbL 1.0. http://osm.org/copyright", "osm_type": "way", "osm_id": 1190266855, "lat": "40.7064001", "lon": "-74.0095353", "class": "highway", "type": "pedestrian", "place_rank": 26, "importance": 0.6088459494861308, "addresstype": "road", "name": "Wall Street", "display_name": "Wall Street, Financial District, Lower Manhattan, Manhattan, New York County, New York, 10005, United States", "boundingbox": ["40.7063780", "40.7064224", "-74.0095707", "-74.0094998"]}]